{
    "fuente": "Glovo", 
    "producto": "Ramo de rosas rojas",
    "direccion": "Calle de las Flores 123, Madrid",
    "codigo_postal": "28001",
    "nombre_mensaje": "Ana López",
    "destinatario_telf": "+34 612 345 678",
    "cliente_nombre": "Carlos Pérez",
    "cliente_telf": "+34 698 765 432",
    "fecha": "2025-11-10",
    "precio": 49.99,
    "observaciones": "Entregar antes de las 12:00. Llamar al llegar.", 
    "horario": "MAÑANA", 
    "mensaje": "Feliz cumpleaños, te mereces todas las flores del mundo." 
}
